{
    "homepage": "https://brave.com",
    "version": "1.78.51",
    "description": "Secure, Fast & Private Web Browser with Adblocker (nightly release)",
    "license": {
        "identifier": "Freeware,BSD-3-Clause,GPL-3.0-only,...",
        "url": "https://github.com/brave/brave-browser/blob/master/LICENSE"
    },
    "architecture": {
        "64bit": {
            "url": "https://ghproxy.cc/https://github.com/brave/brave-browser/releases/download/v1.78.51/brave-v1.78.51-win32-x64.zip",
            "hash": "85f73a81713bc41fb8d69a4f51e6b4dd16b45834b74b925618346ffc500b506b"
        }
    },
    "bin": [
        [
            "brave.exe",
            "brave-nightly"
        ]
    ],
    "shortcuts": [
        [
            "brave.exe",
            "Brave Nightly"
        ]
    ],
    "checkver": {
        "url": "https://github.com/brave/brave-browser/releases",
        "regex": "Nightly v([\\d.]+)"
    },
    "autoupdate": {
        "architecture": {
            "64bit": {
                "url": "https://ghproxy.cc/https://github.com/brave/brave-browser/releases/download/v$version/brave-v$version-win32-x64.zip"
            }
        }
    }
}
