{
    "version": "145.0.7598.0",
    "description": "An open source tool for automated testing of webapps across many browsers",
    "homepage": "https://chromedriver.chromium.org/",
    "license": "BSD-3-Clause",
    "architecture": {
        "64bit": {
            "url": "https://edgedl.me.gvt1.com/edgedl/chrome/chrome-for-testing/145.0.7598.0/win64/chromedriver-win64.zip",
            "hash": "1abd24dbfff7ca704502885213d3d107813d645cce4a0f1d83351a54a0ba3a32",
            "extract_dir": "chromedriver-win64"
        },
        "32bit": {
            "url": "https://edgedl.me.gvt1.com/edgedl/chrome/chrome-for-testing/145.0.7598.0/win32/chromedriver-win32.zip",
            "hash": "1246b354a92716816d5b82950b728f536ea8bc17fecfe7536691f9bc10577c6f",
            "extract_dir": "chromedriver-win32"
        }
    },
    "bin": "chromedriver.exe",
    "checkver": {
        "url": "https://googlechromelabs.github.io/chrome-for-testing/last-known-good-versions-with-downloads.json",
        "jsonpath": "$.channels.Canary.version",
        "regex": "([\\d.]+)"
    },
    "autoupdate": {
        "architecture": {
            "64bit": {
                "url": "https://edgedl.me.gvt1.com/edgedl/chrome/chrome-for-testing/$version/win64/chromedriver-win64.zip"
            },
            "32bit": {
                "url": "https://edgedl.me.gvt1.com/edgedl/chrome/chrome-for-testing/$version/win32/chromedriver-win32.zip"
            }
        }
    }
}
