{
    "version": "121.0.6167.0",
    "description": "An open source tool for automated testing of webapps across many browsers",
    "homepage": "https://chromedriver.chromium.org/",
    "license": "BSD-3-Clause",
    "architecture": {
        "64bit": {
            "url": "https://edgedl.me.gvt1.com/edgedl/chrome/chrome-for-testing/121.0.6167.0/win64/chromedriver-win64.zip",
            "hash": "0c58f9c5f07d4794dd8e1e2f9be6b1250d33e2e2ceb7bc76e09e7ff3b049be24",
            "extract_dir": "chromedriver-win64"
        },
        "32bit": {
            "url": "https://edgedl.me.gvt1.com/edgedl/chrome/chrome-for-testing/121.0.6167.0/win32/chromedriver-win32.zip",
            "hash": "4ecd4f29f95daba9e6cbb30fce48518ea2f0676b2dc225103cd59aaf3bcb1daf",
            "extract_dir": "chromedriver-win32"
        }
    },
    "bin": "chromedriver.exe",
    "checkver": {
        "url": "https://googlechromelabs.github.io/chrome-for-testing/last-known-good-versions-with-downloads.json",
        "jsonpath": "$.channels.Canary.version",
        "regex": "([\\d.]+)"
    },
    "autoupdate": {
        "architecture": {
            "64bit": {
                "url": "https://edgedl.me.gvt1.com/edgedl/chrome/chrome-for-testing/$version/win64/chromedriver-win64.zip"
            },
            "32bit": {
                "url": "https://edgedl.me.gvt1.com/edgedl/chrome/chrome-for-testing/$version/win32/chromedriver-win32.zip"
            }
        }
    }
}
