{
    "version": "0.5.1561",
    "description": "A Git client for simultaneous branches on top of your existing workflow.",
    "homepage": "https://gitbutler.com/",
    "license": "FSL-1.1-MIT",
    "architecture": {
        "64bit": {
            "url": "https://releases.gitbutler.com/releases/nightly/0.5.1561-2439/windows/x86_64/GitButler_Nightly_0.5.1561_x64_en-US.msi",
            "hash": "8bc87317ce1ea8aff02ebaa84bb94ff6c8fdd93ee7ec874c6d340a46d667a20d",
            "extract_dir": "PFiles/GitButler Nightly"
        }
    },
    "shortcuts": [
        [
            "gitbutler-tauri.exe",
            "GitButler Nightly"
        ]
    ],
    "checkver": {
        "url": "https://app.gitbutler.com/downloads",
        "regex": "releases/nightly/([\\d.-]+)-(?<Build>[\\d]+)"
    },
    "autoupdate": {
        "architecture": {
            "64bit": {
                "url": "https://releases.gitbutler.com/releases/nightly/$version-$matchBuild/windows/x86_64/GitButler_Nightly_$version_x64_en-US.msi"
            }
        }
    }
}
