{
    "version": "uFBQ7H",
    "description": "GN is a meta-build system that generates build files for Ninja.",
    "homepage": "https://gn.googlesource.com/gn",
    "license": "BSD-3-Clause",
    "suggest": {
        "ninja": "ninja",
        "Python3": "python"
    },
    "architecture": {
        "64bit": {
            "url": "https://chrome-infra-packages.appspot.com/dl/gn/gn/windows-amd64/+/uFBQ7Hj9iFFfkAauUJJBg0zhYdCb1HV-sISrYdKpkjEC#/gn-windows-amd64.zip",
            "hash": "b85050ec78fd88515f9006ae509241834ce161d09bd4757eb084ab61d2a99231"
        }
    },
    "bin": "gn.exe",
    "checkver": {
        "url": "https://chrome-infra-packages.appspot.com/p/gn/gn/windows-amd64/+/latest",
        "regex": "Instance ID\\S+\\s+<td class=\"user-select-all\">(?<instanceId>(?<short>[\\w-]{6})[\\w-]+)",
        "replace": "${short}"
    },
    "autoupdate": {
        "architecture": {
            "64bit": {
                "url": "https://chrome-infra-packages.appspot.com/dl/gn/gn/windows-amd64/+/$matchInstanceid#/gn-windows-amd64.zip",
                "hash": {
                    "url": "https://chrome-infra-packages.appspot.com/p/gn/gn/windows-amd64/+/latest",
                    "regex": "<b>SHA256</b>\\S+\\s+<td class=\"user-select-all\">$sha256"
                }
            }
        }
    }
}
