{
    "version": "10256",
    "description": "Video editing software based on the MLT Framework, KDE and Qt",
    "homepage": "https://kdenlive.org",
    "license": "GPL-2.0-only",
    "architecture": {
        "64bit": {
            "url": "https://cdn.kde.org/ci-builds/multimedia/kdenlive/master/windows/kdenlive-master-10256-windows-gcc-x86_64.7z",
            "hash": "b646c85c8b4375b2e1ab27cb1d37afa3a2f4a0b17d717bc922a264f634cd3bbf"
        }
    },
    "bin": "bin\\kdenlive.exe",
    "shortcuts": [
        [
            "bin\\kdenlive.exe",
            "Kdenlive Nightly"
        ]
    ],
    "checkver": {
        "url": "https://cdn.kde.org/ci-builds/multimedia/kdenlive/master/windows/",
        "regex": "kdenlive-master-(\\d+)-windows-gcc-x86_64\\.7z"
    },
    "autoupdate": {
        "architecture": {
            "64bit": {
                "url": "https://cdn.kde.org/ci-builds/multimedia/kdenlive/master/windows/kdenlive-master-$version-windows-gcc-x86_64.7z"
            }
        },
        "hash": {
            "url": "$url.sha256"
        }
    }
}
