{
    "version": "9494",
    "description": "Video editing software based on the MLT Framework, KDE and Qt",
    "homepage": "https://kdenlive.org",
    "license": "GPL-2.0-only",
    "architecture": {
        "64bit": {
            "url": "https://cdn.kde.org/ci-builds/multimedia/kdenlive/master/windows/kdenlive-master-9494-windows-gcc-x86_64.7z",
            "hash": "cad32c0805b8b64c6e5d5a26221e57346a06e1fbf4c7fdbf1071393b25cf3fc7"
        }
    },
    "bin": "bin\\kdenlive.exe",
    "shortcuts": [
        [
            "bin\\kdenlive.exe",
            "Kdenlive Nightly"
        ]
    ],
    "checkver": {
        "url": "https://cdn.kde.org/ci-builds/multimedia/kdenlive/master/windows/",
        "regex": "kdenlive-master-(\\d+)-windows-gcc-x86_64\\.7z"
    },
    "autoupdate": {
        "architecture": {
            "64bit": {
                "url": "https://cdn.kde.org/ci-builds/multimedia/kdenlive/master/windows/kdenlive-master-$version-windows-gcc-x86_64.7z"
            }
        },
        "hash": {
            "url": "$url.sha256"
        }
    }
}
