{
    "version": "1.43.0",
    "description": "Kimi CLI is your next CLI agent.",
    "homepage": "https://github.com/MoonshotAI/kimi-cli/",
    "license": "Apache-2.0",
    "architecture": {
        "64bit": {
            "url": "https://gh-proxy.com/https://github.com/MoonshotAI/kimi-cli/releases/download/1.43.0/kimi-1.43.0-x86_64-pc-windows-msvc-onedir.zip",
            "hash": "edf1014ea4ff408f0a2ee2bdad73b1c6eea02f288982a169859e0b362669c48a"
        },
        "arm64": {
            "url": "https://gh-proxy.com/https://github.com/MoonshotAI/kimi-cli/releases/download/1.43.0/kimi-1.43.0-aarch64-pc-windows-msvc-onedir.zip",
            "hash": "b60cf266789120e0cad70c175da3ce5bfd51644fe7b3276248b562c1f0147141"
        }
    },
    "extract_dir": "kimi",
    "bin": "kimi.exe",
    "checkver": {
        "github": "https://github.com/MoonshotAI/kimi-cli"
    },
    "autoupdate": {
        "architecture": {
            "64bit": {
                "url": "https://gh-proxy.com/https://github.com/MoonshotAI/kimi-cli/releases/download/$version/kimi-$version-x86_64-pc-windows-msvc-onedir.zip"
            },
            "arm64": {
                "url": "https://gh-proxy.com/https://github.com/MoonshotAI/kimi-cli/releases/download/$version/kimi-$version-aarch64-pc-windows-msvc-onedir.zip"
            }
        },
        "hash": {
            "url": "$url.sha256"
        }
    }
}
