{
    "version": "6.4.2",
    "description": "A one-click tool for the daily tasks of Arknights, supporting all clients",
    "homepage": "https://github.com/MaaAssistantArknights/MaaAssistantArknights",
    "license": "AGPL-3.0",
    "architecture": {
        "64bit": {
            "url": "https://gh-proxy.com/https://github.com/MaaAssistantArknights/MaaAssistantArknights/releases/download/v6.4.2/MAA-v6.4.2-win-x64.zip",
            "hash": "c2564e9688a18e1f903b26f70c5e75c30b9954379a53a8b3a8edd0dd7c78a3c4"
        }
    },
    "bin": [
        [
            "MAA.exe",
            "MAAAssistantArknights"
        ]
    ],
    "shortcuts": [
        [
            "MAA.exe",
            "Maa Assistant Arknights"
        ]
    ],
    "persist": [
        "cache",
        "config",
        "debug",
        "data"
    ],
    "checkver": "github",
    "autoupdate": {
        "architecture": {
            "64bit": {
                "url": "https://gh-proxy.com/https://github.com/MaaAssistantArknights/MaaAssistantArknights/releases/download/v$version/MAA-v$version-win-x64.zip"
            }
        }
    }
}
