{
    "version": "7.2.2",
    "description": "Command line interface to Sourcegraph",
    "homepage": "https://github.com/sourcegraph/src-cli",
    "license": "Apache-2.0",
    "architecture": {
        "64bit": {
            "url": "https://gh-proxy.com/https://github.com/sourcegraph/src-cli/releases/download/7.2.2/src-cli_7.2.2_windows_amd64.tar.gz",
            "hash": "24c3610751f67c55087b55d8b4f1027c8ab90e2cb2b085f1b0ccf237bb939526"
        }
    },
    "bin": "src.exe",
    "checkver": "github",
    "autoupdate": {
        "url": "https://gh-proxy.com/https://github.com/sourcegraph/src-cli/releases/download/$version/src-cli_$version_windows_amd64.tar.gz",
        "hash": {
            "url": "https://gh-proxy.com/https://github.com/sourcegraph/src-cli/releases/download/$version/src-cli_$version_checksums.txt",
            "regex": "^(\\w+)\\s+src-cli_$version_windows_amd64\\.tar\\.gz$"
        }
    }
}
