{
    "version": "2.107.0-beta.19",
    "description": "Supabase CLI (beta channel).",
    "homepage": "https://supabase.com",
    "license": "MIT",
    "architecture": {
        "64bit": {
            "url": "https://gh-proxy.org/https://github.com/supabase/cli/releases/download/v2.107.0-beta.19/supabase_2.107.0-beta.19_windows_amd64.zip",
            "hash": "a43658972f84fd8ca8db3f73b2760756cd83a7c2dae82e4c38a8c9b7d98e8350"
        },
        "arm64": {
            "url": "https://gh-proxy.org/https://github.com/supabase/cli/releases/download/v2.107.0-beta.19/supabase_2.107.0-beta.19_windows_arm64.zip",
            "hash": "5111ba39680e972196bfcbeba04a8656427b4e7b79c3e8e87575f7372da30afc"
        }
    },
    "bin": "supabase.exe",
    "checkver": {
        "github": "https://api.github.com/repos/supabase/cli/releases",
        "jsonpath": "$[*].tag_name",
        "regex": "\"v([\\d.]+-beta\\.\\d+)\""
    },
    "autoupdate": {
        "architecture": {
            "64bit": {
                "url": "https://gh-proxy.org/https://github.com/supabase/cli/releases/download/v$version/supabase_$version_windows_amd64.zip"
            },
            "arm64": {
                "url": "https://gh-proxy.org/https://github.com/supabase/cli/releases/download/v$version/supabase_$version_windows_arm64.zip"
            }
        },
        "hash": {
            "url": "$baseurl/checksums.txt"
        }
    }
}
