{
    "version": "0.11.4",
    "description": "Feature-Rich TOML Toolkit.",
    "homepage": "https://tombi-toml.github.io/tombi/",
    "license": "MIT",
    "suggest": {
        "vcredist": "vcredist2022"
    },
    "architecture": {
        "64bit": {
            "url": "https://gh-proxy.com/https://github.com/tombi-toml/tombi/releases/download/v0.11.4/tombi-cli-0.11.4-x86_64-pc-windows-msvc.zip",
            "hash": "1fef31f3338b82759e6ad6c8292a1b1aea0640c441cd44ca57599ab23221c061"
        },
        "arm64": {
            "url": "https://gh-proxy.com/https://github.com/tombi-toml/tombi/releases/download/v0.11.4/tombi-cli-0.11.4-aarch64-pc-windows-msvc.zip",
            "hash": "76c68dd31075e9b596bbdff419281cd06348e7355fb51f2b7eed29f375745ab6"
        }
    },
    "bin": "tombi.exe",
    "checkver": {
        "github": "https://github.com/tombi-toml/tombi"
    },
    "autoupdate": {
        "architecture": {
            "64bit": {
                "url": "https://gh-proxy.com/https://github.com/tombi-toml/tombi/releases/download/v$version/tombi-cli-$version-x86_64-pc-windows-msvc.zip"
            },
            "arm64": {
                "url": "https://gh-proxy.com/https://github.com/tombi-toml/tombi/releases/download/v$version/tombi-cli-$version-aarch64-pc-windows-msvc.zip"
            }
        }
    }
}
