{
    "version": "0.49.0",
    "description": "A CLI for Git worktree management, designed for parallel AI agent workflows.",
    "homepage": "https://worktrunk.dev",
    "license": "MIT|Apache-2.0",
    "architecture": {
        "64bit": {
            "url": "https://gh-proxy.com/https://github.com/max-sixty/worktrunk/releases/download/v0.49.0/worktrunk-x86_64-pc-windows-msvc.zip",
            "hash": "79d706ae92a51df75eb9014be12d11ab1b9c4b7e5e561498d8396041c7b82f6b"
        }
    },
    "bin": "git-wt.exe",
    "checkver": {
        "github": "https://github.com/max-sixty/worktrunk"
    },
    "autoupdate": {
        "architecture": {
            "64bit": {
                "url": "https://gh-proxy.com/https://github.com/max-sixty/worktrunk/releases/download/v$version/worktrunk-x86_64-pc-windows-msvc.zip"
            }
        },
        "hash": {
            "url": "$url.sha256"
        }
    }
}
