{
    "version": "2025.11.15.162232",
    "description": "yt-dlp (official) master builds",
    "homepage": "https://github.com/yt-dlp/yt-dlp-master-builds",
    "license": "Freeware",
    "suggest": {
        "ffmpeg": "scoop-cn/ffmpeg-yt-dlp"
    },
    "architecture": {
        "64bit": {
            "url": "https://gh-proxy.com/https://github.com/yt-dlp/yt-dlp-master-builds/releases/download/2025.11.15.162232/yt-dlp.exe",
            "hash": "sha512:17dc5df99c6ac0cde8cfe86952ba848363d74970e0f015875b2d4444638c9c0c3bafed84bc0be18a720394023e305087f1dd2fac788b2d6924bffbfd444d50bb"
        },
        "32bit": {
            "url": "https://gh-proxy.com/https://github.com/yt-dlp/yt-dlp-master-builds/releases/download/2025.11.15.162232/yt-dlp_x86.exe#/yt-dlp.exe",
            "hash": "sha512:61d5f7d217dc9c702fe3d52dedfc2cd526d0ca3bf300b117697862955b106b0855b92aa3f911b6daf7247bcd5681180812beda27e0aaf937b8bed4b5a9bb3980"
        }
    },
    "bin": "yt-dlp.exe",
    "pre_install": "$null = if (!(Test-Path \"$persist_dir/yt-dlp.conf\")) { New-Item \"$dir/yt-dlp.conf\" }",
    "persist": [
        "yt-dlp.conf",
        "ytdlp_plugins",
        "yt-dlp-plugins"
    ],
    "checkver": "github",
    "autoupdate": {
        "architecture": {
            "64bit": {
                "url": "https://gh-proxy.com/https://github.com/yt-dlp/yt-dlp-master-builds/releases/download/$version/yt-dlp.exe"
            },
            "32bit": {
                "url": "https://gh-proxy.com/https://github.com/yt-dlp/yt-dlp-master-builds/releases/download/$version/yt-dlp_x86.exe#/yt-dlp.exe"
            }
        },
        "hash": {
            "url": "$baseurl/SHA2-512SUMS"
        }
    }
}
