{
    "version": "20241104",
    "description": "Zed is a high-performance, multiplayer code editor from the creators of Atom and Tree-sitter. It's also open source.",
    "homepage": "https://zed.dev/",
    "license": "AGPL-3.0, Apache-2.0, GPL-3.0",
    "architecture": {
        "64bit": {
            "url": "https://ghp.ci/https://github.com/deevus/zed-windows-builds/releases/download/20241104/zed-windows.zip",
            "hash": "3b1c717e2fa20ea026cf8e9d8b05da76845c6b995244d76c431bb6d255cebe00"
        }
    },
    "extract_dir": "zed-release",
    "bin": "zed.exe",
    "shortcuts": [
        [
            "zed.exe",
            "Zed"
        ]
    ],
    "checkver": {
        "github": "https://github.com/deevus/zed-windows-builds"
    },
    "autoupdate": {
        "url": "https://ghp.ci/https://github.com/deevus/zed-windows-builds/releases/download/$version/zed-windows.zip"
    }
}
